[
    {
        "ep_id": "P08_17__0",
        "id": "P08_17_0",
        "tar_path": "/share/portal/ys749/EPIC-KITCHENS/P08/rgb_frames/P08_17.tar",
        "image": "./frame_0000000090.jpg",
        "start_image": "./frame_0000000001.jpg",
        "end_image": "./frame_0000000108.jpg",
        "action": "enter kitchen",
        "objects": [
            "lid",
            "hob/cooktop/stovetop",
            "pot"
        ]
    },
    {
        "ep_id": "P08_17__0",
        "id": "P08_17_1",
        "tar_path": "/share/portal/ys749/EPIC-KITCHENS/P08/rgb_frames/P08_17.tar",
        "image": "./frame_0000000128.jpg",
        "start_image": "./frame_0000000110.jpg",
        "end_image": "./frame_0000000217.jpg",
        "action": "adjust temperature",
        "objects": [
            "right hand",
            "lid",
            "hob/cooktop/stovetop",
            "pot"
        ]
    },
    {
        "ep_id": "P08_17__0",
        "id": "P08_17_2",
        "tar_path": "/share/portal/ys749/EPIC-KITCHENS/P08/rgb_frames/P08_17.tar",
        "image": "./frame_0000000269.jpg",
        "start_image": "./frame_0000000247.jpg",
        "end_image": "./frame_0000000316.jpg",
        "action": "open lid",
        "objects": [
            "left hand",
            "right hand",
            "lid",
            "hob/cooktop/stovetop",
            "pot"
        ]
    },
    {
        "ep_id": "P08_17__0",
        "id": "P08_17_3",
        "tar_path": "/share/portal/ys749/EPIC-KITCHENS/P08/rgb_frames/P08_17.tar",
        "image": "./frame_0000000361.jpg",
        "start_image": "./frame_0000000332.jpg",
        "end_image": "./frame_0000000394.jpg",
        "action": "get spoon",
        "objects": [
            "left hand",
            "right hand",
            "food",
            "lid",
            "spoon",
            "pot",
            "hob/cooktop/stovetop"
        ]
    },
    {
        "ep_id": "P08_17__0",
        "id": "P08_17_4",
        "tar_path": "/share/portal/ys749/EPIC-KITCHENS/P08/rgb_frames/P08_17.tar",
        "image": "./frame_0000000805.jpg",
        "start_image": "./frame_0000000398.jpg",
        "end_image": "./frame_0000000923.jpg",
        "action": "mix food in pan",
        "objects": [
            "left hand",
            "right hand",
            "food",
            "lid",
            "spoon",
            "pot",
            "hob/cooktop/stovetop"
        ]
    },
    {
        "ep_id": "P08_17__0",
        "id": "P08_17_5",
        "tar_path": "/share/portal/ys749/EPIC-KITCHENS/P08/rgb_frames/P08_17.tar",
        "image": "./frame_0000001001.jpg",
        "start_image": "./frame_0000000988.jpg",
        "end_image": "./frame_0000001063.jpg",
        "action": "place lid",
        "objects": [
            "left hand",
            "right hand",
            "food",
            "lid",
            "spoon",
            "pot",
            "hob/cooktop/stovetop"
        ]
    },
    {
        "ep_id": "P08_17__0",
        "id": "P08_17_6",
        "tar_path": "/share/portal/ys749/EPIC-KITCHENS/P08/rgb_frames/P08_17.tar",
        "image": "./frame_0000001149.jpg",
        "start_image": "./frame_0000001129.jpg",
        "end_image": "./frame_0000001201.jpg",
        "action": "adjust temperature",
        "objects": [
            "lid",
            "left hand",
            "right hand",
            "hob/cooktop/stovetop",
            "pot"
        ]
    },
    {
        "ep_id": "P08_17__0",
        "id": "P08_17_7",
        "tar_path": "/share/portal/ys749/EPIC-KITCHENS/P08/rgb_frames/P08_17.tar",
        "image": "./frame_0000001408.jpg",
        "start_image": "./frame_0000001389.jpg",
        "end_image": "./frame_0000001442.jpg",
        "action": "get pan",
        "objects": [
            "right hand",
            "hob/cooktop/stovetop",
            "pot"
        ]
    },
    {
        "ep_id": "P08_17__0",
        "id": "P08_17_8",
        "tar_path": "/share/portal/ys749/EPIC-KITCHENS/P08/rgb_frames/P08_17.tar",
        "image": "./frame_0000001533.jpg",
        "start_image": "./frame_0000001448.jpg",
        "end_image": "./frame_0000001555.jpg",
        "action": "place pan",
        "objects": [
            "lid",
            "left hand",
            "right hand",
            "hob/cooktop/stovetop",
            "pot",
            "pan"
        ]
    },
    {
        "ep_id": "P08_17__0",
        "id": "P08_17_9",
        "tar_path": "/share/portal/ys749/EPIC-KITCHENS/P08/rgb_frames/P08_17.tar",
        "image": "./frame_0000001663.jpg",
        "start_image": "./frame_0000001559.jpg",
        "end_image": "./frame_0000001703.jpg",
        "action": "open cooker",
        "objects": [
            "fork",
            "left hand",
            "bowl",
            "right hand",
            "cooker",
            "lid",
            "pot"
        ]
    },
    {
        "ep_id": "P08_17__0",
        "id": "P08_17_10",
        "tar_path": "/share/portal/ys749/EPIC-KITCHENS/P08/rgb_frames/P08_17.tar",
        "image": "./frame_0000002327.jpg",
        "start_image": "./frame_0000002307.jpg",
        "end_image": "./frame_0000002390.jpg",
        "action": "get fork",
        "objects": [
            "fork",
            "left hand",
            "cooker",
            "lid",
            "pot"
        ]
    },
    {
        "ep_id": "P08_17__0",
        "id": "P08_17_12",
        "tar_path": "/share/portal/ys749/EPIC-KITCHENS/P08/rgb_frames/P08_17.tar",
        "image": "./frame_0000002982.jpg",
        "start_image": "./frame_0000002946.jpg",
        "end_image": "./frame_0000003081.jpg",
        "action": "get wrap",
        "objects": [
            "fork",
            "left hand",
            "bowl",
            "right hand",
            "cooker",
            "film"
        ]
    },
    {
        "ep_id": "P08_17__0",
        "id": "P08_17_14",
        "tar_path": "/share/portal/ys749/EPIC-KITCHENS/P08/rgb_frames/P08_17.tar",
        "image": "./frame_0000003285.jpg",
        "start_image": "./frame_0000003225.jpg",
        "end_image": "./frame_0000003474.jpg",
        "action": "close lid",
        "objects": [
            "left hand",
            "bowl",
            "right hand",
            "lid",
            "box"
        ]
    },
    {
        "ep_id": "P08_17__0",
        "id": "P08_17_15",
        "tar_path": "/share/portal/ys749/EPIC-KITCHENS/P08/rgb_frames/P08_17.tar",
        "image": "./frame_0000003515.jpg",
        "start_image": "./frame_0000003475.jpg",
        "end_image": "./frame_0000003533.jpg",
        "action": "open fridge",
        "objects": [
            "left hand",
            "bowl",
            "fridge",
            "lid",
            "box"
        ]
    },
    {
        "ep_id": "P08_17__0",
        "id": "P08_17_17",
        "tar_path": "/share/portal/ys749/EPIC-KITCHENS/P08/rgb_frames/P08_17.tar",
        "image": "./frame_0000003681.jpg",
        "start_image": "./frame_0000003624.jpg",
        "end_image": "./frame_0000003693.jpg",
        "action": "get bowl",
        "objects": [
            "bowl",
            "fridge"
        ]
    },
    {
        "ep_id": "P08_17__0",
        "id": "P08_17_19",
        "tar_path": "/share/portal/ys749/EPIC-KITCHENS/P08/rgb_frames/P08_17.tar",
        "image": "./frame_0000003929.jpg",
        "start_image": "./frame_0000003900.jpg",
        "end_image": "./frame_0000003973.jpg",
        "action": "open cupboard",
        "objects": [
            "cupboard"
        ]
    },
    {
        "ep_id": "P08_17__0",
        "id": "P08_17_21",
        "tar_path": "/share/portal/ys749/EPIC-KITCHENS/P08/rgb_frames/P08_17.tar",
        "image": "./frame_0000004194.jpg",
        "start_image": "./frame_0000004144.jpg",
        "end_image": "./frame_0000005046.jpg",
        "action": "skin the garlic",
        "objects": [
            "right hand",
            "cupboard",
            "chopping board",
            "garlic"
        ]
    },
    {
        "ep_id": "P08_17__0",
        "id": "P08_17_22",
        "tar_path": "/share/portal/ys749/EPIC-KITCHENS/P08/rgb_frames/P08_17.tar",
        "image": "./frame_0000005119.jpg",
        "start_image": "./frame_0000005052.jpg",
        "end_image": "./frame_0000005127.jpg",
        "action": "place garlic on chopping board",
        "objects": [
            "left hand",
            "right hand",
            "chopping board",
            "knife",
            "garlic"
        ]
    },
    {
        "ep_id": "P08_17__0",
        "id": "P08_17_23",
        "tar_path": "/share/portal/ys749/EPIC-KITCHENS/P08/rgb_frames/P08_17.tar",
        "image": "./frame_0000005496.jpg",
        "start_image": "./frame_0000005268.jpg",
        "end_image": "./frame_0000006213.jpg",
        "action": "cut garlic",
        "objects": [
            "left hand",
            "chopping board",
            "right hand",
            "knife",
            "garlic"
        ]
    },
    {
        "ep_id": "P08_17__0",
        "id": "P08_17_24",
        "tar_path": "/share/portal/ys749/EPIC-KITCHENS/P08/rgb_frames/P08_17.tar",
        "image": "./frame_0000006487.jpg",
        "start_image": "./frame_0000006338.jpg",
        "end_image": "./frame_0000006859.jpg",
        "action": "skin garlic",
        "objects": [
            "left hand",
            "chopping board",
            "right hand",
            "knife",
            "garlic"
        ]
    },
    {
        "ep_id": "P08_17__0",
        "id": "P08_17_25",
        "tar_path": "/share/portal/ys749/EPIC-KITCHENS/P08/rgb_frames/P08_17.tar",
        "image": "./frame_0000007178.jpg",
        "start_image": "./frame_0000006869.jpg",
        "end_image": "./frame_0000007289.jpg",
        "action": "chop garlic",
        "objects": [
            "left hand",
            "chopping board",
            "right hand",
            "knife",
            "garlic"
        ]
    },
    {
        "ep_id": "P08_17__0",
        "id": "P08_17_26",
        "tar_path": "/share/portal/ys749/EPIC-KITCHENS/P08/rgb_frames/P08_17.tar",
        "image": "./frame_0000007378.jpg",
        "start_image": "./frame_0000007310.jpg",
        "end_image": "./frame_0000007550.jpg",
        "action": "press garlic",
        "objects": [
            "left hand",
            "chopping board",
            "right hand",
            "knife",
            "garlic",
            "pot"
        ]
    },
    {
        "ep_id": "P08_17__0",
        "id": "P08_17_27",
        "tar_path": "/share/portal/ys749/EPIC-KITCHENS/P08/rgb_frames/P08_17.tar",
        "image": "./frame_0000007675.jpg",
        "start_image": "./frame_0000007624.jpg",
        "end_image": "./frame_0000007800.jpg",
        "action": "check temperature",
        "objects": [
            "left hand",
            "pot",
            "pan",
            "hob/cooktop/stovetop"
        ]
    },
    {
        "ep_id": "P08_17__0",
        "id": "P08_17_28",
        "tar_path": "/share/portal/ys749/EPIC-KITCHENS/P08/rgb_frames/P08_17.tar",
        "image": "./frame_0000008105.jpg",
        "start_image": "./frame_0000008012.jpg",
        "end_image": "./frame_0000008147.jpg",
        "action": "open cupboard",
        "objects": [
            "left hand",
            "pan",
            "hob/cooktop/stovetop"
        ]
    },
    {
        "ep_id": "P08_17__0",
        "id": "P08_17_29",
        "tar_path": "/share/portal/ys749/EPIC-KITCHENS/P08/rgb_frames/P08_17.tar",
        "image": "./frame_0000008347.jpg",
        "start_image": "./frame_0000008183.jpg",
        "end_image": "./frame_0000008384.jpg",
        "action": "get oil",
        "objects": [
            "left hand",
            "pot",
            "pan",
            "olive oil bottle",
            "hob/cooktop/stovetop"
        ]
    },
    {
        "ep_id": "P08_17__0",
        "id": "P08_17_30",
        "tar_path": "/share/portal/ys749/EPIC-KITCHENS/P08/rgb_frames/P08_17.tar",
        "image": "./frame_0000008347.jpg",
        "start_image": "./frame_0000008281.jpg",
        "end_image": "./frame_0000008452.jpg",
        "action": "open it",
        "objects": [
            "left hand",
            "pot",
            "pan",
            "olive oil bottle",
            "hob/cooktop/stovetop"
        ]
    },
    {
        "ep_id": "P08_17__0",
        "id": "P08_17_31",
        "tar_path": "/share/portal/ys749/EPIC-KITCHENS/P08/rgb_frames/P08_17.tar",
        "image": "./frame_0000008672.jpg",
        "start_image": "./frame_0000008466.jpg",
        "end_image": "./frame_0000008736.jpg",
        "action": "pour oil in pan",
        "objects": [
            "left hand",
            "right hand",
            "pot",
            "pan",
            "olive oil bottle",
            "hob/cooktop/stovetop",
            "olive oil"
        ]
    },
    {
        "ep_id": "P08_17__0",
        "id": "P08_17_32",
        "tar_path": "/share/portal/ys749/EPIC-KITCHENS/P08/rgb_frames/P08_17.tar",
        "image": "./frame_0000009245.jpg",
        "start_image": "./frame_0000008952.jpg",
        "end_image": "./frame_0000009297.jpg",
        "action": "pour olive oil in pan",
        "objects": [
            "left hand",
            "right hand",
            "pot",
            "pan",
            "olive oil",
            "hob/cooktop/stovetop",
            "olive oil bottle"
        ]
    },
    {
        "ep_id": "P08_17__0",
        "id": "P08_17_33",
        "tar_path": "/share/portal/ys749/EPIC-KITCHENS/P08/rgb_frames/P08_17.tar",
        "image": "./frame_0000009496.jpg",
        "start_image": "./frame_0000009486.jpg",
        "end_image": "./frame_0000009567.jpg",
        "action": "get spoon",
        "objects": [
            "left hand",
            "spoon",
            "chopping board"
        ]
    },
    {
        "ep_id": "P08_17__0",
        "id": "P08_17_34",
        "tar_path": "/share/portal/ys749/EPIC-KITCHENS/P08/rgb_frames/P08_17.tar",
        "image": "./frame_0000009821.jpg",
        "start_image": "./frame_0000009572.jpg",
        "end_image": "./frame_0000009947.jpg",
        "action": "mix oil",
        "objects": [
            "garlic",
            "left hand",
            "oil",
            "right hand",
            "spoon",
            "pan",
            "chopping board"
        ]
    },
    {
        "ep_id": "P08_17__0",
        "id": "P08_17_36",
        "tar_path": "/share/portal/ys749/EPIC-KITCHENS/P08/rgb_frames/P08_17.tar",
        "image": "./frame_0000010152.jpg",
        "start_image": "./frame_0000010112.jpg",
        "end_image": "./frame_0000010309.jpg",
        "action": "get garlic",
        "objects": [
            "garlic",
            "left hand",
            "right hand",
            "spoon",
            "pot",
            "chopping board"
        ]
    },
    {
        "ep_id": "P08_17__0",
        "id": "P08_17_38",
        "tar_path": "/share/portal/ys749/EPIC-KITCHENS/P08/rgb_frames/P08_17.tar",
        "image": "./frame_0000010632.jpg",
        "start_image": "./frame_0000010569.jpg",
        "end_image": "./frame_0000010656.jpg",
        "action": "get rice",
        "objects": [
            "right hand",
            "spoon",
            "pot",
            "pan",
            "garlic",
            "hob/cooktop/stovetop"
        ]
    },
    {
        "ep_id": "P08_17__0",
        "id": "P08_17_39",
        "tar_path": "/share/portal/ys749/EPIC-KITCHENS/P08/rgb_frames/P08_17.tar",
        "image": "./frame_0000010632.jpg",
        "start_image": "./frame_0000010631.jpg",
        "end_image": "./frame_0000011142.jpg",
        "action": "mix garlic in pan",
        "objects": [
            "right hand",
            "spoon",
            "pot",
            "pan",
            "garlic",
            "hob/cooktop/stovetop"
        ]
    },
    {
        "ep_id": "P08_17__0",
        "id": "P08_17_40",
        "tar_path": "/share/portal/ys749/EPIC-KITCHENS/P08/rgb_frames/P08_17.tar",
        "image": "./frame_0000011309.jpg",
        "start_image": "./frame_0000011175.jpg",
        "end_image": "./frame_0000011575.jpg",
        "action": "pour cooked rice in pan",
        "objects": [
            "left hand",
            "right hand",
            "spoon",
            "cooked rice",
            "pot",
            "pan",
            "sieve",
            "hob/cooktop/stovetop"
        ]
    },
    {
        "ep_id": "P08_17__0",
        "id": "P08_17_41",
        "tar_path": "/share/portal/ys749/EPIC-KITCHENS/P08/rgb_frames/P08_17.tar",
        "image": "./frame_0000012361.jpg",
        "start_image": "./frame_0000011899.jpg",
        "end_image": "./frame_0000012549.jpg",
        "action": "pour rice in pan",
        "objects": [
            "left hand",
            "right hand",
            "spoon",
            "cooked rice",
            "pot",
            "pan",
            "sieve",
            "hob/cooktop/stovetop"
        ]
    },
    {
        "ep_id": "P08_17__0",
        "id": "P08_17_43",
        "tar_path": "/share/portal/ys749/EPIC-KITCHENS/P08/rgb_frames/P08_17.tar",
        "image": "./frame_0000012724.jpg",
        "start_image": "./frame_0000012662.jpg",
        "end_image": "./frame_0000013059.jpg",
        "action": "mix rice in pan",
        "objects": [
            "rice",
            "left hand",
            "bowl",
            "right hand",
            "spoon",
            "pot",
            "pan",
            "hob/cooktop/stovetop"
        ]
    },
    {
        "ep_id": "P08_17__0",
        "id": "P08_17_45",
        "tar_path": "/share/portal/ys749/EPIC-KITCHENS/P08/rgb_frames/P08_17.tar",
        "image": "./frame_0000013203.jpg",
        "start_image": "./frame_0000013115.jpg",
        "end_image": "./frame_0000013423.jpg",
        "action": "pour whisked egg",
        "objects": [
            "fork",
            "rice",
            "left hand",
            "bowl",
            "right hand",
            "whisked egg",
            "spoon",
            "pot",
            "pan"
        ]
    },
    {
        "ep_id": "P08_17__0",
        "id": "P08_17_46",
        "tar_path": "/share/portal/ys749/EPIC-KITCHENS/P08/rgb_frames/P08_17.tar",
        "image": "./frame_0000013505.jpg",
        "start_image": "./frame_0000013429.jpg",
        "end_image": "./frame_0000013544.jpg",
        "action": "place bowl in sink",
        "objects": [
            "fork",
            "left hand",
            "bowl",
            "sink",
            "whisked egg"
        ]
    },
    {
        "ep_id": "P08_17__0",
        "id": "P08_17_47",
        "tar_path": "/share/portal/ys749/EPIC-KITCHENS/P08/rgb_frames/P08_17.tar",
        "image": "./frame_0000014022.jpg",
        "start_image": "./frame_0000013660.jpg",
        "end_image": "./frame_0000014137.jpg",
        "action": "mix egg",
        "objects": [
            "egg",
            "rice",
            "left hand",
            "right hand",
            "hob/cooktop/stovetop",
            "pot",
            "pan"
        ]
    },
    {
        "ep_id": "P08_17__0",
        "id": "P08_17_49",
        "tar_path": "/share/portal/ys749/EPIC-KITCHENS/P08/rgb_frames/P08_17.tar",
        "image": "./frame_0000015186.jpg",
        "start_image": "./frame_0000014316.jpg",
        "end_image": "./frame_0000015331.jpg",
        "action": "mix egg in rice",
        "objects": [
            "rice",
            "left hand",
            "right hand",
            "hob/cooktop/stovetop",
            "pot",
            "pan"
        ]
    },
    {
        "ep_id": "P08_17__0",
        "id": "P08_17_51",
        "tar_path": "/share/portal/ys749/EPIC-KITCHENS/P08/rgb_frames/P08_17.tar",
        "image": "./frame_0000015797.jpg",
        "start_image": "./frame_0000015786.jpg",
        "end_image": "./frame_0000015835.jpg",
        "action": "get bowl",
        "objects": [
            "rice",
            "left hand",
            "bowl",
            "right hand",
            "hob/cooktop/stovetop",
            "pan",
            "pepper shaker"
        ]
    },
    {
        "ep_id": "P08_17__0",
        "id": "P08_17_52",
        "tar_path": "/share/portal/ys749/EPIC-KITCHENS/P08/rgb_frames/P08_17.tar",
        "image": "./frame_0000016097.jpg",
        "start_image": "./frame_0000015863.jpg",
        "end_image": "./frame_0000016131.jpg",
        "action": "mix food in pan",
        "objects": [
            "rice",
            "left hand",
            "bowl",
            "right hand",
            "food",
            "hob/cooktop/stovetop",
            "pot",
            "pan"
        ]
    },
    {
        "ep_id": "P08_17__0",
        "id": "P08_17_54",
        "tar_path": "/share/portal/ys749/EPIC-KITCHENS/P08/rgb_frames/P08_17.tar",
        "image": "./frame_0000016264.jpg",
        "start_image": "./frame_0000016192.jpg",
        "end_image": "./frame_0000016479.jpg",
        "action": "mix food in pan",
        "objects": [
            "rice",
            "bowl",
            "right hand",
            "food",
            "hob/cooktop/stovetop",
            "pot",
            "pan"
        ]
    },
    {
        "ep_id": "P08_17__0",
        "id": "P08_17_55",
        "tar_path": "/share/portal/ys749/EPIC-KITCHENS/P08/rgb_frames/P08_17.tar",
        "image": "./frame_0000017286.jpg",
        "start_image": "./frame_0000017286.jpg",
        "end_image": "./frame_0000017340.jpg",
        "action": "get bowl",
        "objects": [
            "rice",
            "left hand",
            "bowl",
            "right hand",
            "food",
            "hob/cooktop/stovetop",
            "pot",
            "pan"
        ]
    },
    {
        "ep_id": "P08_17__0",
        "id": "P08_17_56",
        "tar_path": "/share/portal/ys749/EPIC-KITCHENS/P08/rgb_frames/P08_17.tar",
        "image": "./frame_0000017418.jpg",
        "start_image": "./frame_0000017364.jpg",
        "end_image": "./frame_0000017540.jpg",
        "action": "put corn in pan",
        "objects": [
            "bell pepper",
            "left hand",
            "bowl",
            "right hand",
            "food",
            "corn",
            "pot",
            "pan"
        ]
    },
    {
        "ep_id": "P08_17__0",
        "id": "P08_17_57",
        "tar_path": "/share/portal/ys749/EPIC-KITCHENS/P08/rgb_frames/P08_17.tar",
        "image": "./frame_0000018560.jpg",
        "start_image": "./frame_0000018376.jpg",
        "end_image": "./frame_0000018630.jpg",
        "action": "put bell pepper in pan",
        "objects": [
            "bell pepper",
            "left hand",
            "bowl",
            "right hand",
            "food",
            "corn",
            "pot",
            "pan"
        ]
    },
    {
        "ep_id": "P08_17__0",
        "id": "P08_17_58",
        "tar_path": "/share/portal/ys749/EPIC-KITCHENS/P08/rgb_frames/P08_17.tar",
        "image": "./frame_0000019102.jpg",
        "start_image": "./frame_0000018803.jpg",
        "end_image": "./frame_0000019985.jpg",
        "action": "mix contents of pan",
        "objects": [
            "left hand",
            "right hand",
            "food",
            "corn",
            "pot",
            "pan"
        ]
    },
    {
        "ep_id": "P08_17__0",
        "id": "P08_17_59",
        "tar_path": "/share/portal/ys749/EPIC-KITCHENS/P08/rgb_frames/P08_17.tar",
        "image": "./frame_0000020153.jpg",
        "start_image": "./frame_0000020019.jpg",
        "end_image": "./frame_0000020189.jpg",
        "action": "shake pan",
        "objects": [
            "left hand",
            "right hand",
            "pot",
            "pan",
            "food"
        ]
    },
    {
        "ep_id": "P08_17__0",
        "id": "P08_17_61",
        "tar_path": "/share/portal/ys749/EPIC-KITCHENS/P08/rgb_frames/P08_17.tar",
        "image": "./frame_0000020480.jpg",
        "start_image": "./frame_0000020436.jpg",
        "end_image": "./frame_0000020491.jpg",
        "action": "open drawer",
        "objects": [
            "drawer",
            "left hand",
            "right hand"
        ]
    },
    {
        "ep_id": "P08_17__0",
        "id": "P08_17_62",
        "tar_path": "/share/portal/ys749/EPIC-KITCHENS/P08/rgb_frames/P08_17.tar",
        "image": "./frame_0000020507.jpg",
        "start_image": "./frame_0000020497.jpg",
        "end_image": "./frame_0000020589.jpg",
        "action": "get fork",
        "objects": [
            "drawer",
            "fork",
            "left hand",
            "right hand"
        ]
    },
    {
        "ep_id": "P08_17__0",
        "id": "P08_17_63",
        "tar_path": "/share/portal/ys749/EPIC-KITCHENS/P08/rgb_frames/P08_17.tar",
        "image": "./frame_0000020722.jpg",
        "start_image": "./frame_0000020683.jpg",
        "end_image": "./frame_0000020810.jpg",
        "action": "taste food",
        "objects": [
            "fork",
            "right hand",
            "food",
            "hob/cooktop/stovetop",
            "spoon",
            "pot",
            "pan"
        ]
    },
    {
        "ep_id": "P08_17__0",
        "id": "P08_17_64",
        "tar_path": "/share/portal/ys749/EPIC-KITCHENS/P08/rgb_frames/P08_17.tar",
        "image": "./frame_0000020895.jpg",
        "start_image": "./frame_0000020816.jpg",
        "end_image": "./frame_0000020922.jpg",
        "action": "place fork",
        "objects": [
            "fork",
            "left hand",
            "right hand",
            "food",
            "hob/cooktop/stovetop",
            "spoon",
            "pot",
            "pan"
        ]
    },
    {
        "ep_id": "P08_17__0",
        "id": "P08_17_65",
        "tar_path": "/share/portal/ys749/EPIC-KITCHENS/P08/rgb_frames/P08_17.tar",
        "image": "./frame_0000021116.jpg",
        "start_image": "./frame_0000020928.jpg",
        "end_image": "./frame_0000021168.jpg",
        "action": "open cupboard",
        "objects": [
            "right hand",
            "cupboard",
            "food",
            "hob/cooktop/stovetop",
            "spoon",
            "pot",
            "pan"
        ]
    },
    {
        "ep_id": "P08_17__0",
        "id": "P08_17_66",
        "tar_path": "/share/portal/ys749/EPIC-KITCHENS/P08/rgb_frames/P08_17.tar",
        "image": "./frame_0000021116.jpg",
        "start_image": "./frame_0000021094.jpg",
        "end_image": "./frame_0000021184.jpg",
        "action": "get soy sauce",
        "objects": [
            "right hand",
            "cupboard",
            "food",
            "hob/cooktop/stovetop",
            "spoon",
            "pot",
            "pan"
        ]
    },
    {
        "ep_id": "P08_17__0",
        "id": "P08_17_67",
        "tar_path": "/share/portal/ys749/EPIC-KITCHENS/P08/rgb_frames/P08_17.tar",
        "image": "./frame_0000021515.jpg",
        "start_image": "./frame_0000021301.jpg",
        "end_image": "./frame_0000021604.jpg",
        "action": "pour soy sauce",
        "objects": [
            "left hand",
            "right hand",
            "food",
            "soy sauce",
            "pot",
            "pan",
            "spatula",
            "hob/cooktop/stovetop",
            "soy sauce bottle lid"
        ]
    },
    {
        "ep_id": "P08_17__0",
        "id": "P08_17_68",
        "tar_path": "/share/portal/ys749/EPIC-KITCHENS/P08/rgb_frames/P08_17.tar",
        "image": "./frame_0000021983.jpg",
        "start_image": "./frame_0000021651.jpg",
        "end_image": "./frame_0000022090.jpg",
        "action": "pour pepper",
        "objects": [
            "pepper shaker",
            "left hand",
            "food",
            "pot",
            "pan",
            "spatula",
            "hob/cooktop/stovetop"
        ]
    },
    {
        "ep_id": "P08_17__0",
        "id": "P08_17_70",
        "tar_path": "/share/portal/ys749/EPIC-KITCHENS/P08/rgb_frames/P08_17.tar",
        "image": "./frame_0000022267.jpg",
        "start_image": "./frame_0000022191.jpg",
        "end_image": "./frame_0000022489.jpg",
        "action": "mix food in pan",
        "objects": [
            "pepper shaker",
            "left hand",
            "right hand",
            "food",
            "soy sauce",
            "pot",
            "pan",
            "spatula",
            "hob/cooktop/stovetop"
        ]
    },
    {
        "ep_id": "P08_17__0",
        "id": "P08_17_71",
        "tar_path": "/share/portal/ys749/EPIC-KITCHENS/P08/rgb_frames/P08_17.tar",
        "image": "./frame_0000022584.jpg",
        "start_image": "./frame_0000022504.jpg",
        "end_image": "./frame_0000022600.jpg",
        "action": "shake pan",
        "objects": [
            "spatula",
            "right hand",
            "food",
            "pot",
            "pan",
            "hob/cooktop/stovetop"
        ]
    },
    {
        "ep_id": "P08_17__0",
        "id": "P08_17_72",
        "tar_path": "/share/portal/ys749/EPIC-KITCHENS/P08/rgb_frames/P08_17.tar",
        "image": "./frame_0000023274.jpg",
        "start_image": "./frame_0000022606.jpg",
        "end_image": "./frame_0000023453.jpg",
        "action": "still shake food in pan",
        "objects": [
            "left hand",
            "spatula",
            "right hand",
            "food",
            "pot",
            "pan",
            "hob/cooktop/stovetop"
        ]
    },
    {
        "ep_id": "P08_17__0",
        "id": "P08_17_73",
        "tar_path": "/share/portal/ys749/EPIC-KITCHENS/P08/rgb_frames/P08_17.tar",
        "image": "./frame_0000023524.jpg",
        "start_image": "./frame_0000023481.jpg",
        "end_image": "./frame_0000023703.jpg",
        "action": "shake pan",
        "objects": [
            "left hand",
            "spatula",
            "right hand",
            "food",
            "pot",
            "pan",
            "hob/cooktop/stovetop"
        ]
    },
    {
        "ep_id": "P08_17__0",
        "id": "P08_17_74",
        "tar_path": "/share/portal/ys749/EPIC-KITCHENS/P08/rgb_frames/P08_17.tar",
        "image": "./frame_0000024325.jpg",
        "start_image": "./frame_0000023709.jpg",
        "end_image": "./frame_0000024459.jpg",
        "action": "mix food in pan",
        "objects": [
            "fork",
            "left hand",
            "spatula",
            "right hand",
            "food",
            "pot",
            "pan",
            "hob/cooktop/stovetop"
        ]
    },
    {
        "ep_id": "P08_17__0",
        "id": "P08_17_75",
        "tar_path": "/share/portal/ys749/EPIC-KITCHENS/P08/rgb_frames/P08_17.tar",
        "image": "./frame_0000024812.jpg",
        "start_image": "./frame_0000024465.jpg",
        "end_image": "./frame_0000024885.jpg",
        "action": "taste food",
        "objects": [
            "fork",
            "spatula",
            "right hand",
            "food",
            "pot",
            "pan",
            "hob/cooktop/stovetop"
        ]
    },
    {
        "ep_id": "P08_17__0",
        "id": "P08_17_76",
        "tar_path": "/share/portal/ys749/EPIC-KITCHENS/P08/rgb_frames/P08_17.tar",
        "image": "./frame_0000025062.jpg",
        "start_image": "./frame_0000024988.jpg",
        "end_image": "./frame_0000025279.jpg",
        "action": "mix food in pan",
        "objects": [
            "fork",
            "left hand",
            "spatula",
            "right hand",
            "food",
            "pot",
            "pan",
            "hob/cooktop/stovetop"
        ]
    },
    {
        "ep_id": "P08_17__0",
        "id": "P08_17_77",
        "tar_path": "/share/portal/ys749/EPIC-KITCHENS/P08/rgb_frames/P08_17.tar",
        "image": "./frame_0000026157.jpg",
        "start_image": "./frame_0000025285.jpg",
        "end_image": "./frame_0000026378.jpg",
        "action": "still mix food in pan",
        "objects": [
            "spatula",
            "right hand",
            "food",
            "pot",
            "pan",
            "hob/cooktop/stovetop"
        ]
    },
    {
        "ep_id": "P08_17__0",
        "id": "P08_17_78",
        "tar_path": "/share/portal/ys749/EPIC-KITCHENS/P08/rgb_frames/P08_17.tar",
        "image": "./frame_0000026467.jpg",
        "start_image": "./frame_0000026384.jpg",
        "end_image": "./frame_0000026508.jpg",
        "action": "shake pan",
        "objects": [
            "left hand",
            "spatula",
            "right hand",
            "food",
            "pot",
            "pan",
            "hob/cooktop/stovetop"
        ]
    },
    {
        "ep_id": "P08_17__0",
        "id": "P08_17_79",
        "tar_path": "/share/portal/ys749/EPIC-KITCHENS/P08/rgb_frames/P08_17.tar",
        "image": "./frame_0000026663.jpg",
        "start_image": "./frame_0000026608.jpg",
        "end_image": "./frame_0000026686.jpg",
        "action": "turn heat on low",
        "objects": [
            "left hand",
            "spatula",
            "right hand",
            "food",
            "pot",
            "pan",
            "hob/cooktop/stovetop"
        ]
    },
    {
        "ep_id": "P08_17__0",
        "id": "P08_17_80",
        "tar_path": "/share/portal/ys749/EPIC-KITCHENS/P08/rgb_frames/P08_17.tar",
        "image": "./frame_0000026825.jpg",
        "start_image": "./frame_0000026770.jpg",
        "end_image": "./frame_0000026857.jpg",
        "action": "close cupboard",
        "objects": [
            "left hand"
        ]
    },
    {
        "ep_id": "P08_17__0",
        "id": "P08_17_81",
        "tar_path": "/share/portal/ys749/EPIC-KITCHENS/P08/rgb_frames/P08_17.tar",
        "image": "./frame_0000027074.jpg",
        "start_image": "./frame_0000026863.jpg",
        "end_image": "./frame_0000027130.jpg",
        "action": "unwrap salad in bowl",
        "objects": [
            "left hand",
            "right hand",
            "spinach leaf",
            "bowl",
            "film"
        ]
    },
    {
        "ep_id": "P08_17__0",
        "id": "P08_17_82",
        "tar_path": "/share/portal/ys749/EPIC-KITCHENS/P08/rgb_frames/P08_17.tar",
        "image": "./frame_0000027183.jpg",
        "start_image": "./frame_0000027158.jpg",
        "end_image": "./frame_0000027233.jpg",
        "action": "open cupboard",
        "objects": [
            "left hand",
            "cupboard"
        ]
    },
    {
        "ep_id": "P08_17__0",
        "id": "P08_17_83",
        "tar_path": "/share/portal/ys749/EPIC-KITCHENS/P08/rgb_frames/P08_17.tar",
        "image": "./frame_0000027344.jpg",
        "start_image": "./frame_0000027238.jpg",
        "end_image": "./frame_0000027371.jpg",
        "action": "get plate",
        "objects": [
            "salad bowl",
            "spinach leaf",
            "plate",
            "right hand",
            "cupboard"
        ]
    },
    {
        "ep_id": "P08_17__0",
        "id": "P08_17_84",
        "tar_path": "/share/portal/ys749/EPIC-KITCHENS/P08/rgb_frames/P08_17.tar",
        "image": "./frame_0000027770.jpg",
        "start_image": "./frame_0000027463.jpg",
        "end_image": "./frame_0000027858.jpg",
        "action": "put spinach leaves on plate",
        "objects": [
            "left hand",
            "salad bowl",
            "spinach leaf",
            "plate",
            "right hand",
            "film"
        ]
    },
    {
        "ep_id": "P08_17__0",
        "id": "P08_17_85",
        "tar_path": "/share/portal/ys749/EPIC-KITCHENS/P08/rgb_frames/P08_17.tar",
        "image": "./frame_0000027910.jpg",
        "start_image": "./frame_0000027848.jpg",
        "end_image": "./frame_0000028025.jpg",
        "action": "close wrap",
        "objects": [
            "left hand",
            "spinach leaf",
            "plate",
            "right hand",
            "bowl",
            "film"
        ]
    },
    {
        "ep_id": "P08_17__0",
        "id": "P08_17_86",
        "tar_path": "/share/portal/ys749/EPIC-KITCHENS/P08/rgb_frames/P08_17.tar",
        "image": "./frame_0000028051.jpg",
        "start_image": "./frame_0000028029.jpg",
        "end_image": "./frame_0000028087.jpg",
        "action": "get salad bowl",
        "objects": [
            "left hand",
            "spinach leaf",
            "plate",
            "right hand",
            "film",
            "bowl"
        ]
    },
    {
        "ep_id": "P08_17__0",
        "id": "P08_17_87",
        "tar_path": "/share/portal/ys749/EPIC-KITCHENS/P08/rgb_frames/P08_17.tar",
        "image": "./frame_0000028205.jpg",
        "start_image": "./frame_0000028180.jpg",
        "end_image": "./frame_0000028260.jpg",
        "action": "place fridge",
        "objects": [
            "left hand",
            "fridge"
        ]
    },
    {
        "ep_id": "P08_17__0",
        "id": "P08_17_88",
        "tar_path": "/share/portal/ys749/EPIC-KITCHENS/P08/rgb_frames/P08_17.tar",
        "image": "./frame_0000028494.jpg",
        "start_image": "./frame_0000028390.jpg",
        "end_image": "./frame_0000028525.jpg",
        "action": "get vegetable rice",
        "objects": [
            "left hand",
            "spinach leaf",
            "plate",
            "right hand",
            "vegetable rice",
            "hob/cooktop/stovetop",
            "pot",
            "pan",
            "spatula"
        ]
    },
    {
        "ep_id": "P08_17__0",
        "id": "P08_17_89",
        "tar_path": "/share/portal/ys749/EPIC-KITCHENS/P08/rgb_frames/P08_17.tar",
        "image": "./frame_0000028647.jpg",
        "start_image": "./frame_0000028531.jpg",
        "end_image": "./frame_0000028965.jpg",
        "action": "place on plate",
        "objects": [
            "left hand",
            "spinach leaf",
            "plate",
            "right hand",
            "vegetable rice",
            "hob/cooktop/stovetop",
            "pot",
            "pan",
            "spatula"
        ]
    },
    {
        "ep_id": "P08_17__0",
        "id": "P08_17_90",
        "tar_path": "/share/portal/ys749/EPIC-KITCHENS/P08/rgb_frames/P08_17.tar",
        "image": "./frame_0000029010.jpg",
        "start_image": "./frame_0000028991.jpg",
        "end_image": "./frame_0000029050.jpg",
        "action": "turn off hob",
        "objects": [
            "right hand",
            "hob/cooktop/stovetop",
            "lid",
            "spoon",
            "pan",
            "vegetable rice"
        ]
    },
    {
        "ep_id": "P08_17__0",
        "id": "P08_17_91",
        "tar_path": "/share/portal/ys749/EPIC-KITCHENS/P08/rgb_frames/P08_17.tar",
        "image": "./frame_0000029252.jpg",
        "start_image": "./frame_0000029171.jpg",
        "end_image": "./frame_0000029281.jpg",
        "action": "take lid off",
        "objects": [
            "left hand",
            "right hand",
            "hob/cooktop/stovetop",
            "lid",
            "spoon",
            "pot",
            "pan",
            "vegetable rice"
        ]
    },
    {
        "ep_id": "P08_17__0",
        "id": "P08_17_92",
        "tar_path": "/share/portal/ys749/EPIC-KITCHENS/P08/rgb_frames/P08_17.tar",
        "image": "./frame_0000029503.jpg",
        "start_image": "./frame_0000029441.jpg",
        "end_image": "./frame_0000029527.jpg",
        "action": "get spoon",
        "objects": [
            "left hand",
            "right hand",
            "hob/cooktop/stovetop",
            "lid",
            "spoon",
            "pan",
            "meat",
            "vegetable rice"
        ]
    },
    {
        "ep_id": "P08_17__0",
        "id": "P08_17_93",
        "tar_path": "/share/portal/ys749/EPIC-KITCHENS/P08/rgb_frames/P08_17.tar",
        "image": "./frame_0000029631.jpg",
        "start_image": "./frame_0000029556.jpg",
        "end_image": "./frame_0000029847.jpg",
        "action": "spoon meat on plate",
        "objects": [
            "left hand",
            "right hand",
            "spoon",
            "pot",
            "pan",
            "meat",
            "vegetable rice"
        ]
    },
    {
        "ep_id": "P08_17__0",
        "id": "P08_17_94",
        "tar_path": "/share/portal/ys749/EPIC-KITCHENS/P08/rgb_frames/P08_17.tar",
        "image": "./frame_0000030284.jpg",
        "start_image": "./frame_0000030254.jpg",
        "end_image": "./frame_0000030389.jpg",
        "action": "spoon meat on plate",
        "objects": [
            "left hand",
            "plate",
            "right hand",
            "spoon",
            "pan",
            "meat"
        ]
    },
    {
        "ep_id": "P08_17__0",
        "id": "P08_17_95",
        "tar_path": "/share/portal/ys749/EPIC-KITCHENS/P08/rgb_frames/P08_17.tar",
        "image": "./frame_0000030572.jpg",
        "start_image": "./frame_0000030461.jpg",
        "end_image": "./frame_0000030609.jpg",
        "action": "spoon meat on plate",
        "objects": [
            "left hand",
            "plate",
            "right hand",
            "spoon",
            "pot",
            "pan",
            "meat",
            "vegetable rice"
        ]
    },
    {
        "ep_id": "P08_17__0",
        "id": "P08_17_96",
        "tar_path": "/share/portal/ys749/EPIC-KITCHENS/P08/rgb_frames/P08_17.tar",
        "image": "./frame_0000031154.jpg",
        "start_image": "./frame_0000031067.jpg",
        "end_image": "./frame_0000031191.jpg",
        "action": "place pan",
        "objects": [
            "left hand",
            "right hand",
            "lid",
            "spoon",
            "pot",
            "pan",
            "vegetable rice"
        ]
    },
    {
        "ep_id": "P08_17__0",
        "id": "P08_17_97",
        "tar_path": "/share/portal/ys749/EPIC-KITCHENS/P08/rgb_frames/P08_17.tar",
        "image": "./frame_0000031276.jpg",
        "start_image": "./frame_0000031197.jpg",
        "end_image": "./frame_0000031332.jpg",
        "action": "place lid on pan",
        "objects": [
            "left hand",
            "right hand",
            "lid",
            "spoon",
            "pot",
            "pan",
            "vegetable rice"
        ]
    },
    {
        "ep_id": "P08_17__0",
        "id": "P08_17_98",
        "tar_path": "/share/portal/ys749/EPIC-KITCHENS/P08/rgb_frames/P08_17.tar",
        "image": "./frame_0000031379.jpg",
        "start_image": "./frame_0000031334.jpg",
        "end_image": "./frame_0000031390.jpg",
        "action": "place spoon",
        "objects": [
            "left hand",
            "bowl",
            "right hand",
            "lid",
            "spoon",
            "pot",
            "pan",
            "hob/cooktop/stovetop"
        ]
    },
    {
        "ep_id": "P08_17__0",
        "id": "P08_17_100",
        "tar_path": "/share/portal/ys749/EPIC-KITCHENS/P08/rgb_frames/P08_17.tar",
        "image": "./frame_0000031659.jpg",
        "start_image": "./frame_0000031648.jpg",
        "end_image": "./frame_0000031817.jpg",
        "action": "get knife",
        "objects": [
            "drawer",
            "left hand",
            "right hand",
            "knife"
        ]
    },
    {
        "ep_id": "P08_17__0",
        "id": "P08_17_99",
        "tar_path": "/share/portal/ys749/EPIC-KITCHENS/P08/rgb_frames/P08_17.tar",
        "image": "./frame_0000031659.jpg",
        "start_image": "./frame_0000031599.jpg",
        "end_image": "./frame_0000031676.jpg",
        "action": "open drawer",
        "objects": [
            "drawer",
            "left hand",
            "right hand",
            "knife"
        ]
    },
    {
        "ep_id": "P08_17__0",
        "id": "P08_17_101",
        "tar_path": "/share/portal/ys749/EPIC-KITCHENS/P08/rgb_frames/P08_17.tar",
        "image": "./frame_0000031893.jpg",
        "start_image": "./frame_0000031830.jpg",
        "end_image": "./frame_0000031936.jpg",
        "action": "get plate",
        "objects": [
            "fork",
            "left hand",
            "plate",
            "right hand",
            "knife",
            "food"
        ]
    },
    {
        "ep_id": "P08_17__0",
        "id": "P08_17_102",
        "tar_path": "/share/portal/ys749/EPIC-KITCHENS/P08/rgb_frames/P08_17.tar",
        "image": "./frame_0000032107.jpg",
        "start_image": "./frame_0000032054.jpg",
        "end_image": "./frame_0000032183.jpg",
        "action": "place fork and knife",
        "objects": [
            "fork",
            "left hand",
            "plate",
            "right hand",
            "knife",
            "food"
        ]
    },
    {
        "ep_id": "P08_17__0",
        "id": "P08_17_103",
        "tar_path": "/share/portal/ys749/EPIC-KITCHENS/P08/rgb_frames/P08_17.tar",
        "image": "./frame_0000032403.jpg",
        "start_image": "./frame_0000032386.jpg",
        "end_image": "./frame_0000032437.jpg",
        "action": "get garlic",
        "objects": [
            "right hand",
            "garlic",
            "cupboard"
        ]
    },
    {
        "ep_id": "P08_17__0",
        "id": "P08_17_104",
        "tar_path": "/share/portal/ys749/EPIC-KITCHENS/P08/rgb_frames/P08_17.tar",
        "image": "./frame_0000032584.jpg",
        "start_image": "./frame_0000032520.jpg",
        "end_image": "./frame_0000032607.jpg",
        "action": "place sponge",
        "objects": [
            "right hand",
            "sponge",
            "sponge handle"
        ]
    },
    {
        "ep_id": "P08_17__0",
        "id": "P08_17_105",
        "tar_path": "/share/portal/ys749/EPIC-KITCHENS/P08/rgb_frames/P08_17.tar",
        "image": "./frame_0000032726.jpg",
        "start_image": "./frame_0000032631.jpg",
        "end_image": "./frame_0000032901.jpg",
        "action": "throw away the garlic bits",
        "objects": [
            "left hand",
            "right hand",
            "garlic skin"
        ]
    },
    {
        "ep_id": "P08_17__0",
        "id": "P08_17_106",
        "tar_path": "/share/portal/ys749/EPIC-KITCHENS/P08/rgb_frames/P08_17.tar",
        "image": "./frame_0000033019.jpg",
        "start_image": "./frame_0000032947.jpg",
        "end_image": "./frame_0000033042.jpg",
        "action": "open dishwasher",
        "objects": [
            "colander",
            "left hand",
            "dishwasher",
            "kitchen towel",
            "sink"
        ]
    },
    {
        "ep_id": "P08_17__0",
        "id": "P08_17_107",
        "tar_path": "/share/portal/ys749/EPIC-KITCHENS/P08/rgb_frames/P08_17.tar",
        "image": "./frame_0000033160.jpg",
        "start_image": "./frame_0000033088.jpg",
        "end_image": "./frame_0000033420.jpg",
        "action": "clean colander",
        "objects": [
            "colander",
            "left hand",
            "right hand",
            "dishwasher",
            "kitchen towel",
            "sink"
        ]
    },
    {
        "ep_id": "P08_17__0",
        "id": "P08_17_108",
        "tar_path": "/share/portal/ys749/EPIC-KITCHENS/P08/rgb_frames/P08_17.tar",
        "image": "./frame_0000033569.jpg",
        "start_image": "./frame_0000033440.jpg",
        "end_image": "./frame_0000033585.jpg",
        "action": "place colander",
        "objects": [
            "right hand",
            "dishwasher",
            "kitchen towel",
            "sink"
        ]
    },
    {
        "ep_id": "P08_17__0",
        "id": "P08_17_109",
        "tar_path": "/share/portal/ys749/EPIC-KITCHENS/P08/rgb_frames/P08_17.tar",
        "image": "./frame_0000033620.jpg",
        "start_image": "./frame_0000033606.jpg",
        "end_image": "./frame_0000033648.jpg",
        "action": "get fork",
        "objects": [
            "fork",
            "right hand",
            "sink"
        ]
    },
    {
        "ep_id": "P08_17__0",
        "id": "P08_17_110",
        "tar_path": "/share/portal/ys749/EPIC-KITCHENS/P08/rgb_frames/P08_17.tar",
        "image": "./frame_0000033684.jpg",
        "start_image": "./frame_0000033664.jpg",
        "end_image": "./frame_0000033707.jpg",
        "action": "place fork",
        "objects": [
            "right hand",
            "dishwasher",
            "sink"
        ]
    },
    {
        "ep_id": "P08_17__0",
        "id": "P08_17_111",
        "tar_path": "/share/portal/ys749/EPIC-KITCHENS/P08/rgb_frames/P08_17.tar",
        "image": "./frame_0000033748.jpg",
        "start_image": "./frame_0000033729.jpg",
        "end_image": "./frame_0000033801.jpg",
        "action": "get bowl",
        "objects": [
            "right hand",
            "bowl",
            "sink"
        ]
    },
    {
        "ep_id": "P08_17__0",
        "id": "P08_17_112",
        "tar_path": "/share/portal/ys749/EPIC-KITCHENS/P08/rgb_frames/P08_17.tar",
        "image": "./frame_0000033869.jpg",
        "start_image": "./frame_0000033850.jpg",
        "end_image": "./frame_0000033891.jpg",
        "action": "open drawer",
        "objects": [
            "left hand",
            "bowl",
            "right hand",
            "kitchen towel",
            "dishwasher",
            "sink"
        ]
    },
    {
        "ep_id": "P08_17__0",
        "id": "P08_17_114",
        "tar_path": "/share/portal/ys749/EPIC-KITCHENS/P08/rgb_frames/P08_17.tar",
        "image": "./frame_0000034191.jpg",
        "start_image": "./frame_0000034072.jpg",
        "end_image": "./frame_0000034228.jpg",
        "action": "wipe off pan",
        "objects": [
            "left hand",
            "right hand",
            "pan",
            "kitchen towel",
            "dishwasher",
            "sink"
        ]
    },
    {
        "ep_id": "P08_17__0",
        "id": "P08_17_115",
        "tar_path": "/share/portal/ys749/EPIC-KITCHENS/P08/rgb_frames/P08_17.tar",
        "image": "./frame_0000034353.jpg",
        "start_image": "./frame_0000034305.jpg",
        "end_image": "./frame_0000034569.jpg",
        "action": "place pan",
        "objects": [
            "bowl",
            "right hand",
            "pan",
            "dishwasher"
        ]
    },
    {
        "ep_id": "P08_17__0",
        "id": "P08_17_116",
        "tar_path": "/share/portal/ys749/EPIC-KITCHENS/P08/rgb_frames/P08_17.tar",
        "image": "./frame_0000034630.jpg",
        "start_image": "./frame_0000034612.jpg",
        "end_image": "./frame_0000034689.jpg",
        "action": "close drawer",
        "objects": [
            "dishwasher"
        ]
    },
    {
        "ep_id": "P08_17__0",
        "id": "P08_17_117",
        "tar_path": "/share/portal/ys749/EPIC-KITCHENS/P08/rgb_frames/P08_17.tar",
        "image": "./frame_0000034770.jpg",
        "start_image": "./frame_0000034698.jpg",
        "end_image": "./frame_0000034786.jpg",
        "action": "close dishwasher",
        "objects": [
            "left hand",
            "sink",
            "right hand",
            "dishwasher"
        ]
    },
    {
        "ep_id": "P08_17__0",
        "id": "P08_17_118",
        "tar_path": "/share/portal/ys749/EPIC-KITCHENS/P08/rgb_frames/P08_17.tar",
        "image": "./frame_0000034856.jpg",
        "start_image": "./frame_0000034818.jpg",
        "end_image": "./frame_0000034939.jpg",
        "action": "wipe off hands",
        "objects": [
            "left hand",
            "right hand",
            "kitchen towel"
        ]
    }
]