[
    {
        "ep_id": "P30_07__0",
        "id": "P30_07_0",
        "tar_path": "/share/portal/ys749/EPIC-KITCHENS/P30/rgb_frames/P30_07.tar",
        "image": "./frame_0000000365.jpg",
        "start_image": "./frame_0000000300.jpg",
        "end_image": "./frame_0000000382.jpg",
        "action": "take kettle",
        "objects": [
            "right hand",
            "kettle",
            "tap",
            "sink"
        ]
    },
    {
        "ep_id": "P30_07__0",
        "id": "P30_07_1",
        "tar_path": "/share/portal/ys749/EPIC-KITCHENS/P30/rgb_frames/P30_07.tar",
        "image": "./frame_0000000452.jpg",
        "start_image": "./frame_0000000418.jpg",
        "end_image": "./frame_0000000519.jpg",
        "action": "turn on tap",
        "objects": [
            "right hand",
            "kettle",
            "left hand",
            "tap",
            "sink"
        ]
    },
    {
        "ep_id": "P30_07__0",
        "id": "P30_07_2",
        "tar_path": "/share/portal/ys749/EPIC-KITCHENS/P30/rgb_frames/P30_07.tar",
        "image": "./frame_0000000645.jpg",
        "start_image": "./frame_0000000486.jpg",
        "end_image": "./frame_0000000718.jpg",
        "action": "fill kettle",
        "objects": [
            "right hand",
            "kettle",
            "left hand",
            "tap",
            "water",
            "sink"
        ]
    },
    {
        "ep_id": "P30_07__0",
        "id": "P30_07_3",
        "tar_path": "/share/portal/ys749/EPIC-KITCHENS/P30/rgb_frames/P30_07.tar",
        "image": "./frame_0000000645.jpg",
        "start_image": "./frame_0000000617.jpg",
        "end_image": "./frame_0000000710.jpg",
        "action": "turn off tap",
        "objects": [
            "right hand",
            "kettle",
            "left hand",
            "tap",
            "water",
            "sink"
        ]
    },
    {
        "ep_id": "P30_07__0",
        "id": "P30_07_4",
        "tar_path": "/share/portal/ys749/EPIC-KITCHENS/P30/rgb_frames/P30_07.tar",
        "image": "./frame_0000000774.jpg",
        "start_image": "./frame_0000000716.jpg",
        "end_image": "./frame_0000000794.jpg",
        "action": "close kettle",
        "objects": [
            "right hand",
            "kettle",
            "left hand"
        ]
    },
    {
        "ep_id": "P30_07__0",
        "id": "P30_07_5",
        "tar_path": "/share/portal/ys749/EPIC-KITCHENS/P30/rgb_frames/P30_07.tar",
        "image": "./frame_0000000774.jpg",
        "start_image": "./frame_0000000761.jpg",
        "end_image": "./frame_0000000897.jpg",
        "action": "put kettle",
        "objects": [
            "right hand",
            "kettle",
            "left hand"
        ]
    },
    {
        "ep_id": "P30_07__0",
        "id": "P30_07_6",
        "tar_path": "/share/portal/ys749/EPIC-KITCHENS/P30/rgb_frames/P30_07.tar",
        "image": "./frame_0000000885.jpg",
        "start_image": "./frame_0000000880.jpg",
        "end_image": "./frame_0000000948.jpg",
        "action": "turn kettle on",
        "objects": [
            "right hand",
            "kettle",
            "left hand",
            "lime squeezer"
        ]
    },
    {
        "ep_id": "P30_07__0",
        "id": "P30_07_7",
        "tar_path": "/share/portal/ys749/EPIC-KITCHENS/P30/rgb_frames/P30_07.tar",
        "image": "./frame_0000001022.jpg",
        "start_image": "./frame_0000000937.jpg",
        "end_image": "./frame_0000001042.jpg",
        "action": "take lime squeezer",
        "objects": [
            "left hand",
            "cupboard"
        ]
    },
    {
        "ep_id": "P30_07__0",
        "id": "P30_07_8",
        "tar_path": "/share/portal/ys749/EPIC-KITCHENS/P30/rgb_frames/P30_07.tar",
        "image": "./frame_0000001062.jpg",
        "start_image": "./frame_0000001006.jpg",
        "end_image": "./frame_0000001076.jpg",
        "action": "open cupboard",
        "objects": [
            "left hand",
            "cupboard"
        ]
    },
    {
        "ep_id": "P30_07__0",
        "id": "P30_07_9",
        "tar_path": "/share/portal/ys749/EPIC-KITCHENS/P30/rgb_frames/P30_07.tar",
        "image": "./frame_0000001143.jpg",
        "start_image": "./frame_0000001082.jpg",
        "end_image": "./frame_0000001174.jpg",
        "action": "put lime squeezer",
        "objects": [
            "lime squeezer",
            "right hand",
            "cupboard"
        ]
    },
    {
        "ep_id": "P30_07__0",
        "id": "P30_07_11",
        "tar_path": "/share/portal/ys749/EPIC-KITCHENS/P30/rgb_frames/P30_07.tar",
        "image": "./frame_0000001262.jpg",
        "start_image": "./frame_0000001239.jpg",
        "end_image": "./frame_0000001296.jpg",
        "action": "open cupboard",
        "objects": [
            "right hand",
            "cupboard"
        ]
    },
    {
        "ep_id": "P30_07__0",
        "id": "P30_07_12",
        "tar_path": "/share/portal/ys749/EPIC-KITCHENS/P30/rgb_frames/P30_07.tar",
        "image": "./frame_0000001502.jpg",
        "start_image": "./frame_0000001452.jpg",
        "end_image": "./frame_0000001516.jpg",
        "action": "close cupboard",
        "objects": [
            "right hand",
            "cupboard"
        ]
    },
    {
        "ep_id": "P30_07__0",
        "id": "P30_07_13",
        "tar_path": "/share/portal/ys749/EPIC-KITCHENS/P30/rgb_frames/P30_07.tar",
        "image": "./frame_0000001637.jpg",
        "start_image": "./frame_0000001627.jpg",
        "end_image": "./frame_0000001686.jpg",
        "action": "take v60",
        "objects": [
            "left hand",
            "v60/pourover coffee maker",
            "mug",
            "filter"
        ]
    },
    {
        "ep_id": "P30_07__0",
        "id": "P30_07_14",
        "tar_path": "/share/portal/ys749/EPIC-KITCHENS/P30/rgb_frames/P30_07.tar",
        "image": "./frame_0000001757.jpg",
        "start_image": "./frame_0000001724.jpg",
        "end_image": "./frame_0000001836.jpg",
        "action": "put filter in bin",
        "objects": [
            "right hand",
            "v60/pourover coffee maker",
            "bin/garbage can/recycling bin",
            "filter"
        ]
    },
    {
        "ep_id": "P30_07__0",
        "id": "P30_07_15",
        "tar_path": "/share/portal/ys749/EPIC-KITCHENS/P30/rgb_frames/P30_07.tar",
        "image": "./frame_0000001908.jpg",
        "start_image": "./frame_0000001893.jpg",
        "end_image": "./frame_0000001965.jpg",
        "action": "take mug",
        "objects": [
            "right hand",
            "left hand",
            "v60/pourover coffee maker",
            "mug"
        ]
    },
    {
        "ep_id": "P30_07__0",
        "id": "P30_07_16",
        "tar_path": "/share/portal/ys749/EPIC-KITCHENS/P30/rgb_frames/P30_07.tar",
        "image": "./frame_0000001993.jpg",
        "start_image": "./frame_0000001990.jpg",
        "end_image": "./frame_0000002049.jpg",
        "action": "turn tap on",
        "objects": [
            "right hand",
            "left hand",
            "tap",
            "mug",
            "sink"
        ]
    },
    {
        "ep_id": "P30_07__0",
        "id": "P30_07_17",
        "tar_path": "/share/portal/ys749/EPIC-KITCHENS/P30/rgb_frames/P30_07.tar",
        "image": "./frame_0000002073.jpg",
        "start_image": "./frame_0000002054.jpg",
        "end_image": "./frame_0000002191.jpg",
        "action": "rinse mug",
        "objects": [
            "right hand",
            "left hand",
            "tap",
            "mug",
            "water",
            "sink"
        ]
    },
    {
        "ep_id": "P30_07__0",
        "id": "P30_07_18",
        "tar_path": "/share/portal/ys749/EPIC-KITCHENS/P30/rgb_frames/P30_07.tar",
        "image": "./frame_0000002444.jpg",
        "start_image": "./frame_0000002197.jpg",
        "end_image": "./frame_0000002572.jpg",
        "action": "wash mug",
        "objects": [
            "right hand",
            "left hand",
            "tap",
            "mug",
            "water",
            "sink"
        ]
    },
    {
        "ep_id": "P30_07__0",
        "id": "P30_07_20",
        "tar_path": "/share/portal/ys749/EPIC-KITCHENS/P30/rgb_frames/P30_07.tar",
        "image": "./frame_0000002799.jpg",
        "start_image": "./frame_0000002769.jpg",
        "end_image": "./frame_0000002937.jpg",
        "action": "rinse mug",
        "objects": [
            "left hand",
            "right hand",
            "tap",
            "mug",
            "water",
            "sink"
        ]
    },
    {
        "ep_id": "P30_07__0",
        "id": "P30_07_22",
        "tar_path": "/share/portal/ys749/EPIC-KITCHENS/P30/rgb_frames/P30_07.tar",
        "image": "./frame_0000003121.jpg",
        "start_image": "./frame_0000003064.jpg",
        "end_image": "./frame_0000003144.jpg",
        "action": "put mug",
        "objects": [
            "right hand",
            "left hand",
            "mug",
            "sink"
        ]
    },
    {
        "ep_id": "P30_07__0",
        "id": "P30_07_23",
        "tar_path": "/share/portal/ys749/EPIC-KITCHENS/P30/rgb_frames/P30_07.tar",
        "image": "./frame_0000003311.jpg",
        "start_image": "./frame_0000003151.jpg",
        "end_image": "./frame_0000003344.jpg",
        "action": "rinse jug",
        "objects": [
            "right hand",
            "left hand",
            "tap",
            "sink"
        ]
    },
    {
        "ep_id": "P30_07__0",
        "id": "P30_07_24",
        "tar_path": "/share/portal/ys749/EPIC-KITCHENS/P30/rgb_frames/P30_07.tar",
        "image": "./frame_0000003473.jpg",
        "start_image": "./frame_0000003430.jpg",
        "end_image": "./frame_0000003486.jpg",
        "action": "take mug",
        "objects": [
            "mug",
            "right hand",
            "left hand"
        ]
    },
    {
        "ep_id": "P30_07__0",
        "id": "P30_07_25",
        "tar_path": "/share/portal/ys749/EPIC-KITCHENS/P30/rgb_frames/P30_07.tar",
        "image": "./frame_0000003507.jpg",
        "start_image": "./frame_0000003493.jpg",
        "end_image": "./frame_0000003550.jpg",
        "action": "empty mug",
        "objects": [
            "mug",
            "right hand",
            "left hand"
        ]
    },
    {
        "ep_id": "P30_07__0",
        "id": "P30_07_26",
        "tar_path": "/share/portal/ys749/EPIC-KITCHENS/P30/rgb_frames/P30_07.tar",
        "image": "./frame_0000003794.jpg",
        "start_image": "./frame_0000003634.jpg",
        "end_image": "./frame_0000003839.jpg",
        "action": "dry mug",
        "objects": [
            "mug",
            "right hand",
            "left hand",
            "tea towel/dish towel"
        ]
    },
    {
        "ep_id": "P30_07__0",
        "id": "P30_07_28",
        "tar_path": "/share/portal/ys749/EPIC-KITCHENS/P30/rgb_frames/P30_07.tar",
        "image": "./frame_0000004026.jpg",
        "start_image": "./frame_0000004013.jpg",
        "end_image": "./frame_0000004120.jpg",
        "action": "continue drying mug",
        "objects": [
            "right hand",
            "mug",
            "tea towel/dish towel"
        ]
    },
    {
        "ep_id": "P30_07__0",
        "id": "P30_07_29",
        "tar_path": "/share/portal/ys749/EPIC-KITCHENS/P30/rgb_frames/P30_07.tar",
        "image": "./frame_0000004192.jpg",
        "start_image": "./frame_0000004169.jpg",
        "end_image": "./frame_0000004282.jpg",
        "action": "hang tea towel",
        "objects": [
            "right hand",
            "left hand",
            "mug",
            "tea towel/dish towel"
        ]
    },
    {
        "ep_id": "P30_07__0",
        "id": "P30_07_30",
        "tar_path": "/share/portal/ys749/EPIC-KITCHENS/P30/rgb_frames/P30_07.tar",
        "image": "./frame_0000004373.jpg",
        "start_image": "./frame_0000004362.jpg",
        "end_image": "./frame_0000004408.jpg",
        "action": "put mug",
        "objects": [
            "left hand",
            "mug"
        ]
    },
    {
        "ep_id": "P30_07__0",
        "id": "P30_07_32",
        "tar_path": "/share/portal/ys749/EPIC-KITCHENS/P30/rgb_frames/P30_07.tar",
        "image": "./frame_0000004503.jpg",
        "start_image": "./frame_0000004462.jpg",
        "end_image": "./frame_0000004510.jpg",
        "action": "put v60",
        "objects": [
            "plate",
            "bowl",
            "drainer"
        ]
    },
    {
        "ep_id": "P30_07__0",
        "id": "P30_07_33",
        "tar_path": "/share/portal/ys749/EPIC-KITCHENS/P30/rgb_frames/P30_07.tar",
        "image": "./frame_0000004560.jpg",
        "start_image": "./frame_0000004543.jpg",
        "end_image": "./frame_0000004620.jpg",
        "action": "take bowl",
        "objects": [
            "right hand",
            "plate",
            "bowl",
            "drainer"
        ]
    },
    {
        "ep_id": "P30_07__0",
        "id": "P30_07_34",
        "tar_path": "/share/portal/ys749/EPIC-KITCHENS/P30/rgb_frames/P30_07.tar",
        "image": "./frame_0000004638.jpg",
        "start_image": "./frame_0000004626.jpg",
        "end_image": "./frame_0000004680.jpg",
        "action": "put bowl",
        "objects": [
            "right hand",
            "left hand",
            "v60",
            "bowl",
            "mug",
            "drainer"
        ]
    },
    {
        "ep_id": "P30_07__0",
        "id": "P30_07_35",
        "tar_path": "/share/portal/ys749/EPIC-KITCHENS/P30/rgb_frames/P30_07.tar",
        "image": "./frame_0000004698.jpg",
        "start_image": "./frame_0000004686.jpg",
        "end_image": "./frame_0000004757.jpg",
        "action": "take plate",
        "objects": [
            "right hand",
            "plate",
            "cupboard",
            "drainer"
        ]
    },
    {
        "ep_id": "P30_07__0",
        "id": "P30_07_37",
        "tar_path": "/share/portal/ys749/EPIC-KITCHENS/P30/rgb_frames/P30_07.tar",
        "image": "./frame_0000004872.jpg",
        "start_image": "./frame_0000004813.jpg",
        "end_image": "./frame_0000004879.jpg",
        "action": "put plate",
        "objects": [
            "right hand",
            "left hand",
            "plate",
            "cupboard",
            "chopping board",
            "drainer"
        ]
    },
    {
        "ep_id": "P30_07__0",
        "id": "P30_07_38",
        "tar_path": "/share/portal/ys749/EPIC-KITCHENS/P30/rgb_frames/P30_07.tar",
        "image": "./frame_0000004960.jpg",
        "start_image": "./frame_0000004882.jpg",
        "end_image": "./frame_0000005002.jpg",
        "action": "take chopping board",
        "objects": [
            "right hand",
            "cupboard",
            "drainer"
        ]
    },
    {
        "ep_id": "P30_07__0",
        "id": "P30_07_39",
        "tar_path": "/share/portal/ys749/EPIC-KITCHENS/P30/rgb_frames/P30_07.tar",
        "image": "./frame_0000005055.jpg",
        "start_image": "./frame_0000005013.jpg",
        "end_image": "./frame_0000005065.jpg",
        "action": "close cupboard",
        "objects": [
            "right hand",
            "coffee bag",
            "cupboard",
            "chopping board",
            "microwave"
        ]
    },
    {
        "ep_id": "P30_07__0",
        "id": "P30_07_41",
        "tar_path": "/share/portal/ys749/EPIC-KITCHENS/P30/rgb_frames/P30_07.tar",
        "image": "./frame_0000005268.jpg",
        "start_image": "./frame_0000005224.jpg",
        "end_image": "./frame_0000005273.jpg",
        "action": "take coffee",
        "objects": [
            "right hand",
            "microwave"
        ]
    },
    {
        "ep_id": "P30_07__0",
        "id": "P30_07_42",
        "tar_path": "/share/portal/ys749/EPIC-KITCHENS/P30/rgb_frames/P30_07.tar",
        "image": "./frame_0000005318.jpg",
        "start_image": "./frame_0000005289.jpg",
        "end_image": "./frame_0000005446.jpg",
        "action": "open bag of coffee",
        "objects": [
            "right hand",
            "left hand",
            "coffee bag",
            "cupboard",
            "microwave",
            "coffee grinder"
        ]
    },
    {
        "ep_id": "P30_07__0",
        "id": "P30_07_43",
        "tar_path": "/share/portal/ys749/EPIC-KITCHENS/P30/rgb_frames/P30_07.tar",
        "image": "./frame_0000005555.jpg",
        "start_image": "./frame_0000005496.jpg",
        "end_image": "./frame_0000005711.jpg",
        "action": "scoop coffee beans",
        "objects": [
            "right hand",
            "left hand",
            "coffee bag",
            "coffee",
            "spoon",
            "coffee grinder"
        ]
    },
    {
        "ep_id": "P30_07__0",
        "id": "P30_07_45",
        "tar_path": "/share/portal/ys749/EPIC-KITCHENS/P30/rgb_frames/P30_07.tar",
        "image": "./frame_0000005840.jpg",
        "start_image": "./frame_0000005833.jpg",
        "end_image": "./frame_0000005904.jpg",
        "action": "turn grinder on",
        "objects": [
            "right hand",
            "left hand",
            "coffee bag",
            "coffee",
            "spoon",
            "coffee grinder"
        ]
    },
    {
        "ep_id": "P30_07__0",
        "id": "P30_07_46",
        "tar_path": "/share/portal/ys749/EPIC-KITCHENS/P30/rgb_frames/P30_07.tar",
        "image": "./frame_0000005896.jpg",
        "start_image": "./frame_0000005883.jpg",
        "end_image": "./frame_0000005944.jpg",
        "action": "close bag of coffee",
        "objects": [
            "right hand",
            "left hand",
            "coffee bag",
            "coffee grinder",
            "spoon"
        ]
    },
    {
        "ep_id": "P30_07__0",
        "id": "P30_07_47",
        "tar_path": "/share/portal/ys749/EPIC-KITCHENS/P30/rgb_frames/P30_07.tar",
        "image": "./frame_0000005998.jpg",
        "start_image": "./frame_0000005954.jpg",
        "end_image": "./frame_0000006007.jpg",
        "action": "put bag of coffee",
        "objects": [
            "left hand",
            "coffee bag"
        ]
    },
    {
        "ep_id": "P30_07__0",
        "id": "P30_07_48",
        "tar_path": "/share/portal/ys749/EPIC-KITCHENS/P30/rgb_frames/P30_07.tar",
        "image": "./frame_0000006124.jpg",
        "start_image": "./frame_0000006031.jpg",
        "end_image": "./frame_0000006291.jpg",
        "action": "move bottle of olive oil",
        "objects": [
            "right hand",
            "olive oil bottle",
            "coffee grinder",
            "filter box",
            "spoon"
        ]
    },
    {
        "ep_id": "P30_07__0",
        "id": "P30_07_49",
        "tar_path": "/share/portal/ys749/EPIC-KITCHENS/P30/rgb_frames/P30_07.tar",
        "image": "./frame_0000006385.jpg",
        "start_image": "./frame_0000006342.jpg",
        "end_image": "./frame_0000006499.jpg",
        "action": "turn coffee grinder off",
        "objects": [
            "right hand",
            "olive oil bottle",
            "coffee grinder",
            "filter box",
            "spoon"
        ]
    },
    {
        "ep_id": "P30_07__0",
        "id": "P30_07_50",
        "tar_path": "/share/portal/ys749/EPIC-KITCHENS/P30/rgb_frames/P30_07.tar",
        "image": "./frame_0000006604.jpg",
        "start_image": "./frame_0000006516.jpg",
        "end_image": "./frame_0000006627.jpg",
        "action": "take filters",
        "objects": [
            "right hand",
            "coffee grinder",
            "filter",
            "filter box",
            "spoon"
        ]
    },
    {
        "ep_id": "P30_07__0",
        "id": "P30_07_51",
        "tar_path": "/share/portal/ys749/EPIC-KITCHENS/P30/rgb_frames/P30_07.tar",
        "image": "./frame_0000006668.jpg",
        "start_image": "./frame_0000006633.jpg",
        "end_image": "./frame_0000006802.jpg",
        "action": "remove filter",
        "objects": [
            "right hand",
            "left hand",
            "filter",
            "filter box"
        ]
    },
    {
        "ep_id": "P30_07__0",
        "id": "P30_07_52",
        "tar_path": "/share/portal/ys749/EPIC-KITCHENS/P30/rgb_frames/P30_07.tar",
        "image": "./frame_0000007058.jpg",
        "start_image": "./frame_0000006784.jpg",
        "end_image": "./frame_0000007215.jpg",
        "action": "fold filter",
        "objects": [
            "right hand",
            "left hand",
            "v60/pourover coffee maker",
            "filter",
            "mug"
        ]
    },
    {
        "ep_id": "P30_07__0",
        "id": "P30_07_53",
        "tar_path": "/share/portal/ys749/EPIC-KITCHENS/P30/rgb_frames/P30_07.tar",
        "image": "./frame_0000007405.jpg",
        "start_image": "./frame_0000007339.jpg",
        "end_image": "./frame_0000007450.jpg",
        "action": "open filter",
        "objects": [
            "right hand",
            "left hand",
            "v60/pourover coffee maker",
            "filter",
            "mug"
        ]
    },
    {
        "ep_id": "P30_07__0",
        "id": "P30_07_54",
        "tar_path": "/share/portal/ys749/EPIC-KITCHENS/P30/rgb_frames/P30_07.tar",
        "image": "./frame_0000007466.jpg",
        "start_image": "./frame_0000007462.jpg",
        "end_image": "./frame_0000007504.jpg",
        "action": "put filter in v60",
        "objects": [
            "right hand",
            "left hand",
            "v60/pourover coffee maker",
            "filter",
            "mug"
        ]
    },
    {
        "ep_id": "P30_07__0",
        "id": "P30_07_55",
        "tar_path": "/share/portal/ys749/EPIC-KITCHENS/P30/rgb_frames/P30_07.tar",
        "image": "./frame_0000007545.jpg",
        "start_image": "./frame_0000007524.jpg",
        "end_image": "./frame_0000007654.jpg",
        "action": "put coffee grounds in v60",
        "objects": [
            "right hand",
            "kettle",
            "left hand",
            "v60/pourover coffee maker",
            "jug",
            "filter",
            "mug",
            "coffee jar"
        ]
    },
    {
        "ep_id": "P30_07__0",
        "id": "P30_07_56",
        "tar_path": "/share/portal/ys749/EPIC-KITCHENS/P30/rgb_frames/P30_07.tar",
        "image": "./frame_0000007978.jpg",
        "start_image": "./frame_0000007965.jpg",
        "end_image": "./frame_0000008035.jpg",
        "action": "take kettle",
        "objects": [
            "right hand",
            "kettle",
            "jug"
        ]
    },
    {
        "ep_id": "P30_07__0",
        "id": "P30_07_57",
        "tar_path": "/share/portal/ys749/EPIC-KITCHENS/P30/rgb_frames/P30_07.tar",
        "image": "./frame_0000008024.jpg",
        "start_image": "./frame_0000008020.jpg",
        "end_image": "./frame_0000008250.jpg",
        "action": "fill jug from kettle",
        "objects": [
            "right hand",
            "kettle",
            "jug"
        ]
    },
    {
        "ep_id": "P30_07__0",
        "id": "P30_07_58",
        "tar_path": "/share/portal/ys749/EPIC-KITCHENS/P30/rgb_frames/P30_07.tar",
        "image": "./frame_0000008272.jpg",
        "start_image": "./frame_0000008256.jpg",
        "end_image": "./frame_0000008359.jpg",
        "action": "put kettle",
        "objects": [
            "right hand",
            "kettle",
            "jug",
            "water"
        ]
    },
    {
        "ep_id": "P30_07__0",
        "id": "P30_07_59",
        "tar_path": "/share/portal/ys749/EPIC-KITCHENS/P30/rgb_frames/P30_07.tar",
        "image": "./frame_0000008465.jpg",
        "start_image": "./frame_0000008365.jpg",
        "end_image": "./frame_0000008481.jpg",
        "action": "take cereal",
        "objects": [
            "bowl",
            "cereal box"
        ]
    },
    {
        "ep_id": "P30_07__0",
        "id": "P30_07_60",
        "tar_path": "/share/portal/ys749/EPIC-KITCHENS/P30/rgb_frames/P30_07.tar",
        "image": "./frame_0000008520.jpg",
        "start_image": "./frame_0000008494.jpg",
        "end_image": "./frame_0000008550.jpg",
        "action": "open cereal",
        "objects": [
            "right hand",
            "left hand",
            "bowl",
            "cereal bag",
            "cereal box",
            "cupboard"
        ]
    },
    {
        "ep_id": "P30_07__0",
        "id": "P30_07_61",
        "tar_path": "/share/portal/ys749/EPIC-KITCHENS/P30/rgb_frames/P30_07.tar",
        "image": "./frame_0000008972.jpg",
        "start_image": "./frame_0000008654.jpg",
        "end_image": "./frame_0000009087.jpg",
        "action": "pour cereal into bowl",
        "objects": [
            "right hand",
            "left hand",
            "cereal bag",
            "bowl",
            "cereal",
            "cereal box",
            "cupboard"
        ]
    },
    {
        "ep_id": "P30_07__0",
        "id": "P30_07_62",
        "tar_path": "/share/portal/ys749/EPIC-KITCHENS/P30/rgb_frames/P30_07.tar",
        "image": "./frame_0000009123.jpg",
        "start_image": "./frame_0000009093.jpg",
        "end_image": "./frame_0000009222.jpg",
        "action": "close cereal bag",
        "objects": [
            "cereal box",
            "right hand",
            "left hand",
            "cereal bag",
            "cereal",
            "bowl"
        ]
    },
    {
        "ep_id": "P30_07__0",
        "id": "P30_07_63",
        "tar_path": "/share/portal/ys749/EPIC-KITCHENS/P30/rgb_frames/P30_07.tar",
        "image": "./frame_0000009304.jpg",
        "start_image": "./frame_0000009225.jpg",
        "end_image": "./frame_0000009348.jpg",
        "action": "close cereal box",
        "objects": [
            "cereal box",
            "right hand",
            "left hand",
            "cereal",
            "bowl"
        ]
    },
    {
        "ep_id": "P30_07__0",
        "id": "P30_07_64",
        "tar_path": "/share/portal/ys749/EPIC-KITCHENS/P30/rgb_frames/P30_07.tar",
        "image": "./frame_0000009369.jpg",
        "start_image": "./frame_0000009354.jpg",
        "end_image": "./frame_0000009441.jpg",
        "action": "put cereal box",
        "objects": [
            "cereal box",
            "right hand"
        ]
    },
    {
        "ep_id": "P30_07__0",
        "id": "P30_07_65",
        "tar_path": "/share/portal/ys749/EPIC-KITCHENS/P30/rgb_frames/P30_07.tar",
        "image": "./frame_0000009611.jpg",
        "start_image": "./frame_0000009425.jpg",
        "end_image": "./frame_0000009882.jpg",
        "action": "pour water into v60",
        "objects": [
            "right hand",
            "left hand",
            "water",
            "jug",
            "v60/pourover coffee maker",
            "filter",
            "coffee",
            "cereal",
            "bowl"
        ]
    },
    {
        "ep_id": "P30_07__0",
        "id": "P30_07_66",
        "tar_path": "/share/portal/ys749/EPIC-KITCHENS/P30/rgb_frames/P30_07.tar",
        "image": "./frame_0000009611.jpg",
        "start_image": "./frame_0000009563.jpg",
        "end_image": "./frame_0000009890.jpg",
        "action": "continue pouring water into v60",
        "objects": [
            "right hand",
            "left hand",
            "water",
            "jug",
            "v60/pourover coffee maker",
            "filter",
            "coffee",
            "cereal",
            "bowl"
        ]
    },
    {
        "ep_id": "P30_07__0",
        "id": "P30_07_67",
        "tar_path": "/share/portal/ys749/EPIC-KITCHENS/P30/rgb_frames/P30_07.tar",
        "image": "./frame_0000009974.jpg",
        "start_image": "./frame_0000009967.jpg",
        "end_image": "./frame_0000010023.jpg",
        "action": "open drawer",
        "objects": [
            "right hand",
            "drawer"
        ]
    },
    {
        "ep_id": "P30_07__0",
        "id": "P30_07_68",
        "tar_path": "/share/portal/ys749/EPIC-KITCHENS/P30/rgb_frames/P30_07.tar",
        "image": "./frame_0000010061.jpg",
        "start_image": "./frame_0000010024.jpg",
        "end_image": "./frame_0000010133.jpg",
        "action": "take spoon",
        "objects": [
            "right hand",
            "spoon",
            "drawer",
            "bowl",
            "cereal"
        ]
    },
    {
        "ep_id": "P30_07__0",
        "id": "P30_07_70",
        "tar_path": "/share/portal/ys749/EPIC-KITCHENS/P30/rgb_frames/P30_07.tar",
        "image": "./frame_0000010451.jpg",
        "start_image": "./frame_0000010359.jpg",
        "end_image": "./frame_0000010467.jpg",
        "action": "open cupboard",
        "objects": [
            "left hand",
            "cupboard",
            "honey bottle"
        ]
    },
    {
        "ep_id": "P30_07__0",
        "id": "P30_07_72",
        "tar_path": "/share/portal/ys749/EPIC-KITCHENS/P30/rgb_frames/P30_07.tar",
        "image": "./frame_0000010554.jpg",
        "start_image": "./frame_0000010540.jpg",
        "end_image": "./frame_0000010585.jpg",
        "action": "close cupboard",
        "objects": [
            "right hand",
            "cupboard"
        ]
    },
    {
        "ep_id": "P30_07__0",
        "id": "P30_07_74",
        "tar_path": "/share/portal/ys749/EPIC-KITCHENS/P30/rgb_frames/P30_07.tar",
        "image": "./frame_0000010872.jpg",
        "start_image": "./frame_0000010756.jpg",
        "end_image": "./frame_0000011115.jpg",
        "action": "squeeze honey onto cereal",
        "objects": [
            "right hand",
            "left hand",
            "cupboard",
            "cereal",
            "honey bottle",
            "bowl",
            "spoon"
        ]
    },
    {
        "ep_id": "P30_07__0",
        "id": "P30_07_73",
        "tar_path": "/share/portal/ys749/EPIC-KITCHENS/P30/rgb_frames/P30_07.tar",
        "image": "./frame_0000010992.jpg",
        "start_image": "./frame_0000010752.jpg",
        "end_image": "./frame_0000011085.jpg",
        "action": "put honey",
        "objects": [
            "right hand",
            "left hand",
            "cupboard",
            "cereal",
            "honey bottle",
            "bowl",
            "spoon"
        ]
    },
    {
        "ep_id": "P30_07__0",
        "id": "P30_07_75",
        "tar_path": "/share/portal/ys749/EPIC-KITCHENS/P30/rgb_frames/P30_07.tar",
        "image": "./frame_0000011114.jpg",
        "start_image": "./frame_0000011105.jpg",
        "end_image": "./frame_0000011178.jpg",
        "action": "close honey",
        "objects": [
            "cupboard"
        ]
    },
    {
        "ep_id": "P30_07__0",
        "id": "P30_07_76",
        "tar_path": "/share/portal/ys749/EPIC-KITCHENS/P30/rgb_frames/P30_07.tar",
        "image": "./frame_0000011232.jpg",
        "start_image": "./frame_0000011208.jpg",
        "end_image": "./frame_0000011297.jpg",
        "action": "open cupboard",
        "objects": [
            "right hand",
            "cupboard"
        ]
    },
    {
        "ep_id": "P30_07__0",
        "id": "P30_07_77",
        "tar_path": "/share/portal/ys749/EPIC-KITCHENS/P30/rgb_frames/P30_07.tar",
        "image": "./frame_0000011412.jpg",
        "start_image": "./frame_0000011375.jpg",
        "end_image": "./frame_0000011418.jpg",
        "action": "close cupboard",
        "objects": [
            "right hand",
            "cupboard"
        ]
    },
    {
        "ep_id": "P30_07__0",
        "id": "P30_07_78",
        "tar_path": "/share/portal/ys749/EPIC-KITCHENS/P30/rgb_frames/P30_07.tar",
        "image": "./frame_0000011515.jpg",
        "start_image": "./frame_0000011500.jpg",
        "end_image": "./frame_0000011593.jpg",
        "action": "open fridge",
        "objects": [
            "right hand",
            "fridge"
        ]
    },
    {
        "ep_id": "P30_07__0",
        "id": "P30_07_79",
        "tar_path": "/share/portal/ys749/EPIC-KITCHENS/P30/rgb_frames/P30_07.tar",
        "image": "./frame_0000011632.jpg",
        "start_image": "./frame_0000011610.jpg",
        "end_image": "./frame_0000011655.jpg",
        "action": "take soy milk",
        "objects": [
            "left hand",
            "fridge",
            "lid",
            "soy milk carton"
        ]
    },
    {
        "ep_id": "P30_07__0",
        "id": "P30_07_80",
        "tar_path": "/share/portal/ys749/EPIC-KITCHENS/P30/rgb_frames/P30_07.tar",
        "image": "./frame_0000011819.jpg",
        "start_image": "./frame_0000011751.jpg",
        "end_image": "./frame_0000012084.jpg",
        "action": "pour soy milk",
        "objects": [
            "right hand",
            "left hand",
            "cereal",
            "bowl",
            "lid",
            "soy milk carton",
            "spoon"
        ]
    },
    {
        "ep_id": "P30_07__0",
        "id": "P30_07_81",
        "tar_path": "/share/portal/ys749/EPIC-KITCHENS/P30/rgb_frames/P30_07.tar",
        "image": "./frame_0000012205.jpg",
        "start_image": "./frame_0000012141.jpg",
        "end_image": "./frame_0000012246.jpg",
        "action": "close fridge",
        "objects": [
            "right hand",
            "fridge"
        ]
    },
    {
        "ep_id": "P30_07__0",
        "id": "P30_07_82",
        "tar_path": "/share/portal/ys749/EPIC-KITCHENS/P30/rgb_frames/P30_07.tar",
        "image": "./frame_0000012416.jpg",
        "start_image": "./frame_0000012379.jpg",
        "end_image": "./frame_0000012516.jpg",
        "action": "squash soy milk carton",
        "objects": [
            "right hand",
            "left hand",
            "soy milk carton",
            "spilled milk",
            "spoon",
            "bowl",
            "cereal"
        ]
    },
    {
        "ep_id": "P30_07__0",
        "id": "P30_07_83",
        "tar_path": "/share/portal/ys749/EPIC-KITCHENS/P30/rgb_frames/P30_07.tar",
        "image": "./frame_0000012625.jpg",
        "start_image": "./frame_0000012541.jpg",
        "end_image": "./frame_0000012664.jpg",
        "action": "continue squashing soy milk carton",
        "objects": [
            "right hand",
            "left hand",
            "soy milk carton",
            "spilled milk",
            "bowl",
            "cereal",
            "spoon"
        ]
    },
    {
        "ep_id": "P30_07__0",
        "id": "P30_07_85",
        "tar_path": "/share/portal/ys749/EPIC-KITCHENS/P30/rgb_frames/P30_07.tar",
        "image": "./frame_0000012810.jpg",
        "start_image": "./frame_0000012787.jpg",
        "end_image": "./frame_0000012889.jpg",
        "action": "put soy milk carton in recycling bin",
        "objects": [
            "right hand",
            "recycling bin",
            "soy milk carton"
        ]
    },
    {
        "ep_id": "P30_07__0",
        "id": "P30_07_86",
        "tar_path": "/share/portal/ys749/EPIC-KITCHENS/P30/rgb_frames/P30_07.tar",
        "image": "./frame_0000013128.jpg",
        "start_image": "./frame_0000012988.jpg",
        "end_image": "./frame_0000013218.jpg",
        "action": "take knife and fork and put into drawer",
        "objects": [
            "fork",
            "right hand",
            "left hand",
            "sponge",
            "knife",
            "sink",
            "drawer",
            "water",
            "washing bowl"
        ]
    },
    {
        "ep_id": "P30_07__0",
        "id": "P30_07_87",
        "tar_path": "/share/portal/ys749/EPIC-KITCHENS/P30/rgb_frames/P30_07.tar",
        "image": "./frame_0000013315.jpg",
        "start_image": "./frame_0000013224.jpg",
        "end_image": "./frame_0000013357.jpg",
        "action": "rinse sponge",
        "objects": [
            "right hand",
            "sponge",
            "tap",
            "sink",
            "water",
            "washing bowl"
        ]
    },
    {
        "ep_id": "P30_07__0",
        "id": "P30_07_88",
        "tar_path": "/share/portal/ys749/EPIC-KITCHENS/P30/rgb_frames/P30_07.tar",
        "image": "./frame_0000013696.jpg",
        "start_image": "./frame_0000013353.jpg",
        "end_image": "./frame_0000013802.jpg",
        "action": "wipe surface",
        "objects": [
            "right hand",
            "sponge",
            "surface",
            "sink",
            "spoon",
            "cereal",
            "bowl",
            "spilled milk"
        ]
    },
    {
        "ep_id": "P30_07__0",
        "id": "P30_07_89",
        "tar_path": "/share/portal/ys749/EPIC-KITCHENS/P30/rgb_frames/P30_07.tar",
        "image": "./frame_0000013696.jpg",
        "start_image": "./frame_0000013654.jpg",
        "end_image": "./frame_0000013869.jpg",
        "action": "continue wiping surface",
        "objects": [
            "right hand",
            "sponge",
            "surface",
            "sink",
            "spoon",
            "cereal",
            "bowl",
            "spilled milk"
        ]
    },
    {
        "ep_id": "P30_07__0",
        "id": "P30_07_90",
        "tar_path": "/share/portal/ys749/EPIC-KITCHENS/P30/rgb_frames/P30_07.tar",
        "image": "./frame_0000013913.jpg",
        "start_image": "./frame_0000013894.jpg",
        "end_image": "./frame_0000014044.jpg",
        "action": "rinse sponge",
        "objects": [
            "right hand",
            "sponge",
            "tap",
            "surface",
            "sink",
            "washing bowl",
            "water"
        ]
    },
    {
        "ep_id": "P30_07__0",
        "id": "P30_07_91",
        "tar_path": "/share/portal/ys749/EPIC-KITCHENS/P30/rgb_frames/P30_07.tar",
        "image": "./frame_0000014166.jpg",
        "start_image": "./frame_0000014094.jpg",
        "end_image": "./frame_0000014193.jpg",
        "action": "rinse sponge",
        "objects": [
            "right hand",
            "sponge",
            "tap",
            "surface",
            "sink",
            "washing bowl",
            "water"
        ]
    },
    {
        "ep_id": "P30_07__0",
        "id": "P30_07_92",
        "tar_path": "/share/portal/ys749/EPIC-KITCHENS/P30/rgb_frames/P30_07.tar",
        "image": "./frame_0000014296.jpg",
        "start_image": "./frame_0000014199.jpg",
        "end_image": "./frame_0000014623.jpg",
        "action": "scrub surface",
        "objects": [
            "right hand",
            "left hand",
            "sponge",
            "surface",
            "cereal",
            "bowl",
            "spoon"
        ]
    },
    {
        "ep_id": "P30_07__0",
        "id": "P30_07_93",
        "tar_path": "/share/portal/ys749/EPIC-KITCHENS/P30/rgb_frames/P30_07.tar",
        "image": "./frame_0000014521.jpg",
        "start_image": "./frame_0000014405.jpg",
        "end_image": "./frame_0000014619.jpg",
        "action": "wipe surface",
        "objects": [
            "right hand",
            "sponge",
            "surface",
            "cereal",
            "bowl",
            "spoon"
        ]
    },
    {
        "ep_id": "P30_07__0",
        "id": "P30_07_95",
        "tar_path": "/share/portal/ys749/EPIC-KITCHENS/P30/rgb_frames/P30_07.tar",
        "image": "./frame_0000014857.jpg",
        "start_image": "./frame_0000014797.jpg",
        "end_image": "./frame_0000014977.jpg",
        "action": "move cereal",
        "objects": [
            "right hand",
            "left hand",
            "sponge",
            "surface",
            "cereal",
            "bowl",
            "spoon"
        ]
    },
    {
        "ep_id": "P30_07__0",
        "id": "P30_07_96",
        "tar_path": "/share/portal/ys749/EPIC-KITCHENS/P30/rgb_frames/P30_07.tar",
        "image": "./frame_0000014857.jpg",
        "start_image": "./frame_0000014808.jpg",
        "end_image": "./frame_0000014982.jpg",
        "action": "move v60",
        "objects": [
            "right hand",
            "left hand",
            "sponge",
            "surface",
            "cereal",
            "bowl",
            "spoon"
        ]
    },
    {
        "ep_id": "P30_07__0",
        "id": "P30_07_97",
        "tar_path": "/share/portal/ys749/EPIC-KITCHENS/P30/rgb_frames/P30_07.tar",
        "image": "./frame_0000015046.jpg",
        "start_image": "./frame_0000014996.jpg",
        "end_image": "./frame_0000015205.jpg",
        "action": "scrub surface",
        "objects": [
            "right hand",
            "sponge",
            "surface",
            "cereal",
            "bowl",
            "spoon"
        ]
    },
    {
        "ep_id": "P30_07__0",
        "id": "P30_07_99",
        "tar_path": "/share/portal/ys749/EPIC-KITCHENS/P30/rgb_frames/P30_07.tar",
        "image": "./frame_0000015384.jpg",
        "start_image": "./frame_0000015226.jpg",
        "end_image": "./frame_0000015961.jpg",
        "action": "continue scrubbing surface",
        "objects": [
            "right hand",
            "left hand",
            "surface",
            "sponge",
            "spoon",
            "cereal",
            "bowl"
        ]
    },
    {
        "ep_id": "P30_07__0",
        "id": "P30_07_100",
        "tar_path": "/share/portal/ys749/EPIC-KITCHENS/P30/rgb_frames/P30_07.tar",
        "image": "./frame_0000016185.jpg",
        "start_image": "./frame_0000016117.jpg",
        "end_image": "./frame_0000016358.jpg",
        "action": "wipe surface",
        "objects": [
            "right hand",
            "surface",
            "sponge"
        ]
    },
    {
        "ep_id": "P30_07__0",
        "id": "P30_07_102",
        "tar_path": "/share/portal/ys749/EPIC-KITCHENS/P30/rgb_frames/P30_07.tar",
        "image": "./frame_0000016575.jpg",
        "start_image": "./frame_0000016485.jpg",
        "end_image": "./frame_0000016609.jpg",
        "action": "continue wiping surface",
        "objects": [
            "right hand",
            "surface",
            "sponge"
        ]
    },
    {
        "ep_id": "P30_07__0",
        "id": "P30_07_103",
        "tar_path": "/share/portal/ys749/EPIC-KITCHENS/P30/rgb_frames/P30_07.tar",
        "image": "./frame_0000016662.jpg",
        "start_image": "./frame_0000016565.jpg",
        "end_image": "./frame_0000016785.jpg",
        "action": "continue wiping surface",
        "objects": [
            "right hand",
            "surface",
            "sponge",
            "cereal",
            "bowl",
            "spoon"
        ]
    },
    {
        "ep_id": "P30_07__0",
        "id": "P30_07_104",
        "tar_path": "/share/portal/ys749/EPIC-KITCHENS/P30/rgb_frames/P30_07.tar",
        "image": "./frame_0000016662.jpg",
        "start_image": "./frame_0000016630.jpg",
        "end_image": "./frame_0000016780.jpg",
        "action": "continue wiping surface",
        "objects": [
            "right hand",
            "surface",
            "sponge",
            "cereal",
            "bowl",
            "spoon"
        ]
    },
    {
        "ep_id": "P30_07__0",
        "id": "P30_07_105",
        "tar_path": "/share/portal/ys749/EPIC-KITCHENS/P30/rgb_frames/P30_07.tar",
        "image": "./frame_0000017148.jpg",
        "start_image": "./frame_0000017100.jpg",
        "end_image": "./frame_0000017371.jpg",
        "action": "dry hands",
        "objects": [
            "right hand",
            "tea towel/dish towel"
        ]
    }
]